kblab/__init__.py
kblab/alto_to_json.xsl
kblab/archive.py
kblab/exceptions.py
kblab/fixalto.xsl
kblab/helpers.py
kblab/httparchive.py
kblab/httppackage.py
kblab/package.py
kblab/result.py
kblab/utils.py
kblab_client-0.0.16a0.dist-info/METADATA
kblab_client-0.0.16a0.dist-info/WHEEL
kblab_client-0.0.16a0.dist-info/top_level.txt
kblab_client-0.0.16a0.dist-info/RECORD
