Metadata-Version: 2.1
Name: kblab-client
Version: 0.0.16a0
Summary: KB lab client
Home-page: https://github.com/kungbib/kblab
Author: Martin Malmsten
Author-email: martin.malmsten@kb.se
License: UNKNOWN
Platform: UNKNOWN
Requires-Dist: requests
Requires-Dist: pyyaml
Requires-Dist: lxml
Requires-Dist: htfile
